swift_gen.py
SwiftCodeGen-0.1.dist-info/DESCRIPTION.rst
SwiftCodeGen-0.1.dist-info/METADATA
SwiftCodeGen-0.1.dist-info/RECORD
SwiftCodeGen-0.1.dist-info/WHEEL
SwiftCodeGen-0.1.dist-info/entry_points.txt
SwiftCodeGen-0.1.dist-info/metadata.json
SwiftCodeGen-0.1.dist-info/top_level.txt
