Metadata-Version: 2.0
Name: SwiftCodeGen
Version: 0.1
Summary: A command line utility to generate model and web service classes in Swift programming language.
Home-page: https://github.com/akhilraj-rajkumar/swift-code-gen
Author: Akhilraj Rajkumar
Author-email: akhilr46@gmail.com
License: Apache License
Platform: UNKNOWN
Requires-Dist: Click
Requires-Dist: enum
Requires-Dist: mod-pbxproj
Requires-Dist: pathlib
Requires-Dist: python-dateutil
Requires-Dist: python-string-utils
Requires-Dist: stemming
